agent_framework_devui/__init__.py
agent_framework_devui/_cli.py
agent_framework_devui/_conversations.py
agent_framework_devui/_deployment.py
agent_framework_devui/_discovery.py
agent_framework_devui/_executor.py
agent_framework_devui/_mapper.py
agent_framework_devui/_server.py
agent_framework_devui/_session.py
agent_framework_devui/_tracing.py
agent_framework_devui/_utils.py
agent_framework_devui/_openai/__init__.py
agent_framework_devui/_openai/_executor.py
agent_framework_devui/models/__init__.py
agent_framework_devui/models/_discovery_models.py
agent_framework_devui/models/_openai_custom.py
agent_framework_devui/ui/agentframework.svg
agent_framework_devui/ui/index.html
agent_framework_devui/ui/assets/index.css
agent_framework_devui/ui/assets/index.js
agent_framework_devui-1.0.0b260130.dist-info/entry_points.txt
agent_framework_devui-1.0.0b260130.dist-info/licenses/LICENSE
agent_framework_devui-1.0.0b260130.dist-info/WHEEL
agent_framework_devui-1.0.0b260130.dist-info/METADATA
agent_framework_devui-1.0.0b260130.dist-info/RECORD
