Metadata-Version: 2.4
Name: agent-framework-devui
Version: 1.0.0b260130
Summary: Debug UI for Microsoft Agent Framework with OpenAI-compatible API server.
Author-email: Microsoft <af-support@microsoft.com>
Requires-Python: >=3.10
Classifier: License :: OSI Approved :: MIT License
Classifier: Development Status :: 4 - Beta
Classifier: Intended Audience :: Developers
Classifier: Programming Language :: Python :: 3
Classifier: Programming Language :: Python :: 3.10
Classifier: Programming Language :: Python :: 3.11
Classifier: Programming Language :: Python :: 3.12
Classifier: Programming Language :: Python :: 3.13
Classifier: Programming Language :: Python :: 3.14
Classifier: Typing :: Typed
License-File: LICENSE
Requires-Dist: agent-framework-core
Requires-Dist: fastapi>=0.104.0
Requires-Dist: uvicorn[standard]>=0.24.0
Requires-Dist: python-dotenv>=1.0.0
Requires-Dist: pytest>=7.0.0 ; extra == "all"
Requires-Dist: watchdog>=3.0.0 ; extra == "all"
Requires-Dist: pytest>=7.0.0 ; extra == "dev"
Requires-Dist: watchdog>=3.0.0 ; extra == "dev"
Project-URL: homepage, https://github.com/microsoft/agent-framework
Project-URL: issues, https://github.com/microsoft/agent-framework/issues
Project-URL: release_notes, https://github.com/microsoft/agent-framework/releases?q=tag%3Apython-1&expanded=true
Project-URL: source, https://github.com/microsoft/agent-framework/tree/main/python
Provides-Extra: all
Provides-Extra: dev
